{
  "namespaces": [
    "public"
  ],
  "name": "public",
  "tables": [
    {
      "columns": {
        "id": {
          "name": "id",
          "type": "text",
          "unsigned": false,
          "autoincrement": false,
          "primary": false,
          "nullable": false,
          "mappedType": "text"
        },
        "code": {
          "name": "code",
          "type": "text",
          "unsigned": false,
          "autoincrement": false,
          "primary": false,
          "nullable": false,
          "mappedType": "text"
        },
        "unit": {
          "name": "unit",
          "type": "text",
          "unsigned": false,
          "autoincrement": false,
          "primary": false,
          "nullable": true,
          "mappedType": "text"
        },
        "created_at": {
          "name": "created_at",
          "type": "timestamptz",
          "unsigned": false,
          "autoincrement": false,
          "primary": false,
          "nullable": false,
          "length": 6,
          "default": "now()",
          "mappedType": "datetime"
        },
        "updated_at": {
          "name": "updated_at",
          "type": "timestamptz",
          "unsigned": false,
          "autoincrement": false,
          "primary": false,
          "nullable": false,
          "length": 6,
          "default": "now()",
          "mappedType": "datetime"
        },
        "deleted_at": {
          "name": "deleted_at",
          "type": "timestamptz",
          "unsigned": false,
          "autoincrement": false,
          "primary": false,
          "nullable": true,
          "length": 6,
          "mappedType": "datetime"
        }
      },
      "name": "attribute",
      "schema": "public",
      "indexes": [
        {
          "keyName": "IDX_attribute_deleted_at",
          "columnNames": [],
          "composite": false,
          "constraint": false,
          "primary": false,
          "unique": false,
          "expression": "CREATE INDEX IF NOT EXISTS \"IDX_attribute_deleted_at\" ON \"attribute\" (\"deleted_at\") WHERE deleted_at IS NULL"
        },
        {
          "keyName": "attribute_pkey",
          "columnNames": [
            "id"
          ],
          "composite": false,
          "constraint": true,
          "primary": true,
          "unique": true
        }
      ],
      "checks": [],
      "foreignKeys": {},
      "nativeEnums": {}
    },
    {
      "columns": {
        "id": {
          "name": "id",
          "type": "text",
          "unsigned": false,
          "autoincrement": false,
          "primary": false,
          "nullable": false,
          "mappedType": "text"
        },
        "attribute_id": {
          "name": "attribute_id",
          "type": "text",
          "unsigned": false,
          "autoincrement": false,
          "primary": false,
          "nullable": false,
          "mappedType": "text"
        },
        "value_number": {
          "name": "value_number",
          "type": "integer",
          "unsigned": false,
          "autoincrement": false,
          "primary": false,
          "nullable": true,
          "mappedType": "integer"
        },
        "value_text": {
          "name": "value_text",
          "type": "text",
          "unsigned": false,
          "autoincrement": false,
          "primary": false,
          "nullable": true,
          "mappedType": "text"
        },
        "created_at": {
          "name": "created_at",
          "type": "timestamptz",
          "unsigned": false,
          "autoincrement": false,
          "primary": false,
          "nullable": false,
          "length": 6,
          "default": "now()",
          "mappedType": "datetime"
        },
        "updated_at": {
          "name": "updated_at",
          "type": "timestamptz",
          "unsigned": false,
          "autoincrement": false,
          "primary": false,
          "nullable": false,
          "length": 6,
          "default": "now()",
          "mappedType": "datetime"
        },
        "deleted_at": {
          "name": "deleted_at",
          "type": "timestamptz",
          "unsigned": false,
          "autoincrement": false,
          "primary": false,
          "nullable": true,
          "length": 6,
          "mappedType": "datetime"
        }
      },
      "name": "attribute_value",
      "schema": "public",
      "indexes": [
        {
          "keyName": "IDX_attribute_value_attribute_id",
          "columnNames": [],
          "composite": false,
          "constraint": false,
          "primary": false,
          "unique": false,
          "expression": "CREATE INDEX IF NOT EXISTS \"IDX_attribute_value_attribute_id\" ON \"attribute_value\" (\"attribute_id\") WHERE deleted_at IS NULL"
        },
        {
          "keyName": "IDX_attribute_value_deleted_at",
          "columnNames": [],
          "composite": false,
          "constraint": false,
          "primary": false,
          "unique": false,
          "expression": "CREATE INDEX IF NOT EXISTS \"IDX_attribute_value_deleted_at\" ON \"attribute_value\" (\"deleted_at\") WHERE deleted_at IS NULL"
        },
        {
          "keyName": "attribute_value_pkey",
          "columnNames": [
            "id"
          ],
          "composite": false,
          "constraint": true,
          "primary": true,
          "unique": true
        }
      ],
      "checks": [],
      "foreignKeys": {
        "attribute_value_attribute_id_foreign": {
          "constraintName": "attribute_value_attribute_id_foreign",
          "columnNames": [
            "attribute_id"
          ],
          "localTableName": "public.attribute_value",
          "referencedColumnNames": [
            "id"
          ],
          "referencedTableName": "public.attribute",
          "updateRule": "cascade"
        }
      },
      "nativeEnums": {}
    },
    {
      "columns": {
        "id": {
          "name": "id",
          "type": "text",
          "unsigned": false,
          "autoincrement": false,
          "primary": false,
          "nullable": false,
          "mappedType": "text"
        },
        "name": {
          "name": "name",
          "type": "text",
          "unsigned": false,
          "autoincrement": false,
          "primary": false,
          "nullable": false,
          "mappedType": "text"
        },
        "code": {
          "name": "code",
          "type": "text",
          "unsigned": false,
          "autoincrement": false,
          "primary": false,
          "nullable": true,
          "mappedType": "text"
        },
        "created_at": {
          "name": "created_at",
          "type": "timestamptz",
          "unsigned": false,
          "autoincrement": false,
          "primary": false,
          "nullable": false,
          "length": 6,
          "default": "now()",
          "mappedType": "datetime"
        },
        "updated_at": {
          "name": "updated_at",
          "type": "timestamptz",
          "unsigned": false,
          "autoincrement": false,
          "primary": false,
          "nullable": false,
          "length": 6,
          "default": "now()",
          "mappedType": "datetime"
        },
        "deleted_at": {
          "name": "deleted_at",
          "type": "timestamptz",
          "unsigned": false,
          "autoincrement": false,
          "primary": false,
          "nullable": true,
          "length": 6,
          "mappedType": "datetime"
        }
      },
      "name": "brand",
      "schema": "public",
      "indexes": [
        {
          "keyName": "IDX_brand_deleted_at",
          "columnNames": [],
          "composite": false,
          "constraint": false,
          "primary": false,
          "unique": false,
          "expression": "CREATE INDEX IF NOT EXISTS \"IDX_brand_deleted_at\" ON \"brand\" (\"deleted_at\") WHERE deleted_at IS NULL"
        },
        {
          "keyName": "brand_pkey",
          "columnNames": [
            "id"
          ],
          "composite": false,
          "constraint": true,
          "primary": true,
          "unique": true
        }
      ],
      "checks": [],
      "foreignKeys": {},
      "nativeEnums": {}
    },
    {
      "columns": {
        "id": {
          "name": "id",
          "type": "text",
          "unsigned": false,
          "autoincrement": false,
          "primary": false,
          "nullable": false,
          "mappedType": "text"
        },
        "reference_type": {
          "name": "reference_type",
          "type": "text",
          "unsigned": false,
          "autoincrement": false,
          "primary": false,
          "nullable": false,
          "mappedType": "text"
        },
        "reference_value": {
          "name": "reference_value",
          "type": "text",
          "unsigned": false,
          "autoincrement": false,
          "primary": false,
          "nullable": false,
          "mappedType": "text"
        },
        "manufacturer": {
          "name": "manufacturer",
          "type": "text",
          "unsigned": false,
          "autoincrement": false,
          "primary": false,
          "nullable": false,
          "mappedType": "text"
        },
        "created_at": {
          "name": "created_at",
          "type": "timestamptz",
          "unsigned": false,
          "autoincrement": false,
          "primary": false,
          "nullable": false,
          "length": 6,
          "default": "now()",
          "mappedType": "datetime"
        },
        "updated_at": {
          "name": "updated_at",
          "type": "timestamptz",
          "unsigned": false,
          "autoincrement": false,
          "primary": false,
          "nullable": false,
          "length": 6,
          "default": "now()",
          "mappedType": "datetime"
        },
        "deleted_at": {
          "name": "deleted_at",
          "type": "timestamptz",
          "unsigned": false,
          "autoincrement": false,
          "primary": false,
          "nullable": true,
          "length": 6,
          "mappedType": "datetime"
        }
      },
      "name": "part_reference",
      "schema": "public",
      "indexes": [
        {
          "keyName": "IDX_part_reference_deleted_at",
          "columnNames": [],
          "composite": false,
          "constraint": false,
          "primary": false,
          "unique": false,
          "expression": "CREATE INDEX IF NOT EXISTS \"IDX_part_reference_deleted_at\" ON \"part_reference\" (\"deleted_at\") WHERE deleted_at IS NULL"
        },
        {
          "keyName": "part_reference_pkey",
          "columnNames": [
            "id"
          ],
          "composite": false,
          "constraint": true,
          "primary": true,
          "unique": true
        }
      ],
      "checks": [],
      "foreignKeys": {},
      "nativeEnums": {}
    },
    {
      "columns": {
        "id": {
          "name": "id",
          "type": "text",
          "unsigned": false,
          "autoincrement": false,
          "primary": false,
          "nullable": false,
          "mappedType": "text"
        },
        "name": {
          "name": "name",
          "type": "text",
          "unsigned": false,
          "autoincrement": false,
          "primary": false,
          "nullable": false,
          "mappedType": "text"
        },
        "created_at": {
          "name": "created_at",
          "type": "timestamptz",
          "unsigned": false,
          "autoincrement": false,
          "primary": false,
          "nullable": false,
          "length": 6,
          "default": "now()",
          "mappedType": "datetime"
        },
        "updated_at": {
          "name": "updated_at",
          "type": "timestamptz",
          "unsigned": false,
          "autoincrement": false,
          "primary": false,
          "nullable": false,
          "length": 6,
          "default": "now()",
          "mappedType": "datetime"
        },
        "deleted_at": {
          "name": "deleted_at",
          "type": "timestamptz",
          "unsigned": false,
          "autoincrement": false,
          "primary": false,
          "nullable": true,
          "length": 6,
          "mappedType": "datetime"
        }
      },
      "name": "vehicle_brand",
      "schema": "public",
      "indexes": [
        {
          "keyName": "IDX_vehicle_brand_deleted_at",
          "columnNames": [],
          "composite": false,
          "constraint": false,
          "primary": false,
          "unique": false,
          "expression": "CREATE INDEX IF NOT EXISTS \"IDX_vehicle_brand_deleted_at\" ON \"vehicle_brand\" (\"deleted_at\") WHERE deleted_at IS NULL"
        },
        {
          "keyName": "vehicle_brand_pkey",
          "columnNames": [
            "id"
          ],
          "composite": false,
          "constraint": true,
          "primary": true,
          "unique": true
        }
      ],
      "checks": [],
      "foreignKeys": {},
      "nativeEnums": {}
    },
    {
      "columns": {
        "id": {
          "name": "id",
          "type": "text",
          "unsigned": false,
          "autoincrement": false,
          "primary": false,
          "nullable": false,
          "mappedType": "text"
        },
        "name": {
          "name": "name",
          "type": "text",
          "unsigned": false,
          "autoincrement": false,
          "primary": false,
          "nullable": false,
          "mappedType": "text"
        },
        "brand_id": {
          "name": "brand_id",
          "type": "text",
          "unsigned": false,
          "autoincrement": false,
          "primary": false,
          "nullable": false,
          "mappedType": "text"
        },
        "created_at": {
          "name": "created_at",
          "type": "timestamptz",
          "unsigned": false,
          "autoincrement": false,
          "primary": false,
          "nullable": false,
          "length": 6,
          "default": "now()",
          "mappedType": "datetime"
        },
        "updated_at": {
          "name": "updated_at",
          "type": "timestamptz",
          "unsigned": false,
          "autoincrement": false,
          "primary": false,
          "nullable": false,
          "length": 6,
          "default": "now()",
          "mappedType": "datetime"
        },
        "deleted_at": {
          "name": "deleted_at",
          "type": "timestamptz",
          "unsigned": false,
          "autoincrement": false,
          "primary": false,
          "nullable": true,
          "length": 6,
          "mappedType": "datetime"
        }
      },
      "name": "vehicle_model",
      "schema": "public",
      "indexes": [
        {
          "keyName": "IDX_vehicle_model_brand_id",
          "columnNames": [],
          "composite": false,
          "constraint": false,
          "primary": false,
          "unique": false,
          "expression": "CREATE INDEX IF NOT EXISTS \"IDX_vehicle_model_brand_id\" ON \"vehicle_model\" (\"brand_id\") WHERE deleted_at IS NULL"
        },
        {
          "keyName": "IDX_vehicle_model_deleted_at",
          "columnNames": [],
          "composite": false,
          "constraint": false,
          "primary": false,
          "unique": false,
          "expression": "CREATE INDEX IF NOT EXISTS \"IDX_vehicle_model_deleted_at\" ON \"vehicle_model\" (\"deleted_at\") WHERE deleted_at IS NULL"
        },
        {
          "keyName": "vehicle_model_pkey",
          "columnNames": [
            "id"
          ],
          "composite": false,
          "constraint": true,
          "primary": true,
          "unique": true
        }
      ],
      "checks": [],
      "foreignKeys": {
        "vehicle_model_brand_id_foreign": {
          "constraintName": "vehicle_model_brand_id_foreign",
          "columnNames": [
            "brand_id"
          ],
          "localTableName": "public.vehicle_model",
          "referencedColumnNames": [
            "id"
          ],
          "referencedTableName": "public.vehicle_brand",
          "updateRule": "cascade"
        }
      },
      "nativeEnums": {}
    },
    {
      "columns": {
        "id": {
          "name": "id",
          "type": "text",
          "unsigned": false,
          "autoincrement": false,
          "primary": false,
          "nullable": false,
          "mappedType": "text"
        },
        "year_from": {
          "name": "year_from",
          "type": "integer",
          "unsigned": false,
          "autoincrement": false,
          "primary": false,
          "nullable": false,
          "mappedType": "integer"
        },
        "year_to": {
          "name": "year_to",
          "type": "integer",
          "unsigned": false,
          "autoincrement": false,
          "primary": false,
          "nullable": true,
          "mappedType": "integer"
        },
        "model_id": {
          "name": "model_id",
          "type": "text",
          "unsigned": false,
          "autoincrement": false,
          "primary": false,
          "nullable": false,
          "mappedType": "text"
        },
        "created_at": {
          "name": "created_at",
          "type": "timestamptz",
          "unsigned": false,
          "autoincrement": false,
          "primary": false,
          "nullable": false,
          "length": 6,
          "default": "now()",
          "mappedType": "datetime"
        },
        "updated_at": {
          "name": "updated_at",
          "type": "timestamptz",
          "unsigned": false,
          "autoincrement": false,
          "primary": false,
          "nullable": false,
          "length": 6,
          "default": "now()",
          "mappedType": "datetime"
        },
        "deleted_at": {
          "name": "deleted_at",
          "type": "timestamptz",
          "unsigned": false,
          "autoincrement": false,
          "primary": false,
          "nullable": true,
          "length": 6,
          "mappedType": "datetime"
        }
      },
      "name": "vehicle_generation",
      "schema": "public",
      "indexes": [
        {
          "keyName": "IDX_vehicle_generation_model_id",
          "columnNames": [],
          "composite": false,
          "constraint": false,
          "primary": false,
          "unique": false,
          "expression": "CREATE INDEX IF NOT EXISTS \"IDX_vehicle_generation_model_id\" ON \"vehicle_generation\" (\"model_id\") WHERE deleted_at IS NULL"
        },
        {
          "keyName": "IDX_vehicle_generation_deleted_at",
          "columnNames": [],
          "composite": false,
          "constraint": false,
          "primary": false,
          "unique": false,
          "expression": "CREATE INDEX IF NOT EXISTS \"IDX_vehicle_generation_deleted_at\" ON \"vehicle_generation\" (\"deleted_at\") WHERE deleted_at IS NULL"
        },
        {
          "keyName": "vehicle_generation_pkey",
          "columnNames": [
            "id"
          ],
          "composite": false,
          "constraint": true,
          "primary": true,
          "unique": true
        }
      ],
      "checks": [],
      "foreignKeys": {
        "vehicle_generation_model_id_foreign": {
          "constraintName": "vehicle_generation_model_id_foreign",
          "columnNames": [
            "model_id"
          ],
          "localTableName": "public.vehicle_generation",
          "referencedColumnNames": [
            "id"
          ],
          "referencedTableName": "public.vehicle_model",
          "updateRule": "cascade"
        }
      },
      "nativeEnums": {}
    },
    {
      "columns": {
        "id": {
          "name": "id",
          "type": "text",
          "unsigned": false,
          "autoincrement": false,
          "primary": false,
          "nullable": false,
          "mappedType": "text"
        },
        "engine_code": {
          "name": "engine_code",
          "type": "text",
          "unsigned": false,
          "autoincrement": false,
          "primary": false,
          "nullable": false,
          "mappedType": "text"
        },
        "fuel_type": {
          "name": "fuel_type",
          "type": "text",
          "unsigned": false,
          "autoincrement": false,
          "primary": false,
          "nullable": false,
          "mappedType": "text"
        },
        "displacement_cc": {
          "name": "displacement_cc",
          "type": "integer",
          "unsigned": false,
          "autoincrement": false,
          "primary": false,
          "nullable": false,
          "mappedType": "integer"
        },
        "horsepower": {
          "name": "horsepower",
          "type": "integer",
          "unsigned": false,
          "autoincrement": false,
          "primary": false,
          "nullable": false,
          "mappedType": "integer"
        },
        "generation_id": {
          "name": "generation_id",
          "type": "text",
          "unsigned": false,
          "autoincrement": false,
          "primary": false,
          "nullable": false,
          "mappedType": "text"
        },
        "created_at": {
          "name": "created_at",
          "type": "timestamptz",
          "unsigned": false,
          "autoincrement": false,
          "primary": false,
          "nullable": false,
          "length": 6,
          "default": "now()",
          "mappedType": "datetime"
        },
        "updated_at": {
          "name": "updated_at",
          "type": "timestamptz",
          "unsigned": false,
          "autoincrement": false,
          "primary": false,
          "nullable": false,
          "length": 6,
          "default": "now()",
          "mappedType": "datetime"
        },
        "deleted_at": {
          "name": "deleted_at",
          "type": "timestamptz",
          "unsigned": false,
          "autoincrement": false,
          "primary": false,
          "nullable": true,
          "length": 6,
          "mappedType": "datetime"
        }
      },
      "name": "vehicle_engine",
      "schema": "public",
      "indexes": [
        {
          "keyName": "IDX_vehicle_engine_generation_id",
          "columnNames": [],
          "composite": false,
          "constraint": false,
          "primary": false,
          "unique": false,
          "expression": "CREATE INDEX IF NOT EXISTS \"IDX_vehicle_engine_generation_id\" ON \"vehicle_engine\" (\"generation_id\") WHERE deleted_at IS NULL"
        },
        {
          "keyName": "IDX_vehicle_engine_deleted_at",
          "columnNames": [],
          "composite": false,
          "constraint": false,
          "primary": false,
          "unique": false,
          "expression": "CREATE INDEX IF NOT EXISTS \"IDX_vehicle_engine_deleted_at\" ON \"vehicle_engine\" (\"deleted_at\") WHERE deleted_at IS NULL"
        },
        {
          "keyName": "vehicle_engine_pkey",
          "columnNames": [
            "id"
          ],
          "composite": false,
          "constraint": true,
          "primary": true,
          "unique": true
        }
      ],
      "checks": [],
      "foreignKeys": {
        "vehicle_engine_generation_id_foreign": {
          "constraintName": "vehicle_engine_generation_id_foreign",
          "columnNames": [
            "generation_id"
          ],
          "localTableName": "public.vehicle_engine",
          "referencedColumnNames": [
            "id"
          ],
          "referencedTableName": "public.vehicle_generation",
          "updateRule": "cascade"
        }
      },
      "nativeEnums": {}
    },
    {
      "columns": {
        "id": {
          "name": "id",
          "type": "text",
          "unsigned": false,
          "autoincrement": false,
          "primary": false,
          "nullable": false,
          "mappedType": "text"
        },
        "vehicle_engine_id": {
          "name": "vehicle_engine_id",
          "type": "text",
          "unsigned": false,
          "autoincrement": false,
          "primary": false,
          "nullable": false,
          "mappedType": "text"
        },
        "position": {
          "name": "position",
          "type": "text",
          "unsigned": false,
          "autoincrement": false,
          "primary": false,
          "nullable": false,
          "mappedType": "text"
        },
        "criteria": {
          "name": "criteria",
          "type": "jsonb",
          "unsigned": false,
          "autoincrement": false,
          "primary": false,
          "nullable": true,
          "mappedType": "json"
        },
        "created_at": {
          "name": "created_at",
          "type": "timestamptz",
          "unsigned": false,
          "autoincrement": false,
          "primary": false,
          "nullable": false,
          "length": 6,
          "default": "now()",
          "mappedType": "datetime"
        },
        "updated_at": {
          "name": "updated_at",
          "type": "timestamptz",
          "unsigned": false,
          "autoincrement": false,
          "primary": false,
          "nullable": false,
          "length": 6,
          "default": "now()",
          "mappedType": "datetime"
        },
        "deleted_at": {
          "name": "deleted_at",
          "type": "timestamptz",
          "unsigned": false,
          "autoincrement": false,
          "primary": false,
          "nullable": true,
          "length": 6,
          "mappedType": "datetime"
        }
      },
      "name": "fitment",
      "schema": "public",
      "indexes": [
        {
          "keyName": "IDX_fitment_vehicle_engine_id",
          "columnNames": [],
          "composite": false,
          "constraint": false,
          "primary": false,
          "unique": false,
          "expression": "CREATE INDEX IF NOT EXISTS \"IDX_fitment_vehicle_engine_id\" ON \"fitment\" (\"vehicle_engine_id\") WHERE deleted_at IS NULL"
        },
        {
          "keyName": "IDX_fitment_deleted_at",
          "columnNames": [],
          "composite": false,
          "constraint": false,
          "primary": false,
          "unique": false,
          "expression": "CREATE INDEX IF NOT EXISTS \"IDX_fitment_deleted_at\" ON \"fitment\" (\"deleted_at\") WHERE deleted_at IS NULL"
        },
        {
          "keyName": "fitment_pkey",
          "columnNames": [
            "id"
          ],
          "composite": false,
          "constraint": true,
          "primary": true,
          "unique": true
        }
      ],
      "checks": [],
      "foreignKeys": {
        "fitment_vehicle_engine_id_foreign": {
          "constraintName": "fitment_vehicle_engine_id_foreign",
          "columnNames": [
            "vehicle_engine_id"
          ],
          "localTableName": "public.fitment",
          "referencedColumnNames": [
            "id"
          ],
          "referencedTableName": "public.vehicle_engine",
          "updateRule": "cascade"
        }
      },
      "nativeEnums": {}
    }
  ],
  "nativeEnums": {}
}
